[
	{
		"name": "Atul Singh",
		"image": "https://drive.google.com/uc?id=1FzkmE7DWr3oqTSPipBiIQAUqaP7eBzZv",
		"instagram": "https://www.instagram.com/atulsingh.pks/",
		"facebook": "",
		"github": "https://github.com/AtulSingh-Emyre/",
		"linkedin": "https://www.linkedin.com/in/atul-singh-457610195/"
	},
  {
    "name": "Tabish Khalid Halim",
    "image": "https://drive.google.com/uc?id=1mmTtd8Cb2hMzD9NRLEfhGx8yE4ZceXKc",
    "instagram":"https://www.instagram.com/thesnagtalker007/",
    "facebook": "",
    "github":"https://github.com/tkhalim14/",
    "linkedin":"https://www.linkedin.com/in/tabish-khalid-halim-27209b201/"
  }
  
]